{
    "products": [
        {
            "id": 1,
            "name": "White Shirt",
            "catagory": "men",
            "oldPrice": 700,
            "newPrice": 0,
            "rating": 4
        },
        {
            "id": 2,
            "name": "Black Watch",
            "catagory": "watch",
            "oldPrice": 700,
            "newPrice": 550,
            "rating": 3.5
        },
        {
            "id": 3,
            "name": "IPhone 15 pro",
            "catagory": "phone",
            "oldPrice": 700,
            "newPrice": 0,
            "rating": 5
        },
        {
            "id": 4,
            "name": "Benson",
            "catagory": "watch",
            "oldPrice": 700,
            "newPrice": 0,
            "rating": 4.5
        },
        {
            "id": 5,
            "name": "Infiniz Hot 10 Play",
            "catagory": "phone",
            "oldPrice": 21000,
            "newPrice": 19500,
            "rating": 4
        },
        {
            "id": 6,
            "name": "Women White Shirt",
            "catagory": "women",
            "oldPrice": 700,
            "newPrice": 500,
            "rating": 4
        },
        {
            "id": 7,
            "name": "Controller",
            "catagory": "game",
            "oldPrice": 1500,
            "newPrice": 1200,
            "rating": 2
        },
        {
            "id": 9,
            "name": "Audionic super headphone",
            "catagory": "headphone",
            "oldPrice": 700,
            "newPrice": 0,
            "rating": 3
        }
    ]
}